crud_generator.py
crud_generator-1.0.2.dist-info/METADATA
crud_generator-1.0.2.dist-info/WHEEL
crud_generator-1.0.2.dist-info/top_level.txt
crud_generator-1.0.2.dist-info/RECORD
