Metadata-Version: 2.1
Name: crud-generator
Version: 1.0.2
Summary: This will generate a crud operations (crud.py) for your Database tables.
Home-page: UNKNOWN
License: UNKNOWN
Platform: UNKNOWN
